MetaDataManager/__init__.py
MetaDataManager/main.py
metadatamanager-0.1.0.dist-info/LICENSE
metadatamanager-0.1.0.dist-info/METADATA
metadatamanager-0.1.0.dist-info/WHEEL
metadatamanager-0.1.0.dist-info/RECORD
