Metadata-Version: 2.3
Name: metadatamanager
Version: 0.1.0
Summary: `MetadataManager` 是一个简单的 JSON 元数据管理器，旨在方便地读取、写入和操作 JSON 文件。它提供了一系列方法来管理嵌套的 JSON 数据结构，支持添加、删除、读取和更新操作。
Author: a木木
Author-email: mumuwj0001@163.com
Requires-Python: >=3.10
Classifier: Programming Language :: Python :: 3
Classifier: Programming Language :: Python :: 3.10
Classifier: Programming Language :: Python :: 3.11
Classifier: Programming Language :: Python :: 3.12
Classifier: Programming Language :: Python :: 3.13
